{
    "botName" : "turing",
    "randSeed" : 23,
    "nBots" : 500,
    "formation": "pile",
    "timeStep" : 0.0416666,
    "simulationTime" : 10000,
    "showCommsRadius" : 0,
    "showComms" : 0,
    "distributePercent" : 0.40,
    "displayWidth"  : 1500,
    "displayHeight" : 1200,
    "displayScale"  : 0.75,
    "showHist" : 0,
    "storeHistory": 0,
    "saveVideo" : 0,
    "saveVideoN" : 200,
    "commsRadius": 120,
    "msgSuccessRate": 0.7,
    "stepsPerFrame" : 1000,    
    "GUI" : 1
}
